py3html/__init__.py
py3html-1.0.2.dist-info/LICENSE
py3html-1.0.2.dist-info/WHEEL
py3html-1.0.2.dist-info/METADATA
py3html-1.0.2.dist-info/RECORD
