Metadata-Version: 2.1
Name: py3html
Version: 1.0.2
Summary: A very simple tool to generate html with python code.
Home-page: https://ozcanyarimdunya.github.io/py3html/
License: MIT
Keywords: py3html,html
Author: Özcan Yarımdünya
Author-email: ozcanyd@gmail.com
Requires-Python: >=3.9,<4.0
Classifier: Development Status :: 4 - Beta
Classifier: License :: OSI Approved :: MIT License
Classifier: Operating System :: OS Independent
Classifier: Programming Language :: Python :: 3
Classifier: Programming Language :: Python :: 3.9
Classifier: Programming Language :: Python :: 3.10
Classifier: Programming Language :: Python :: 3.11
Classifier: Programming Language :: Python :: 3
Classifier: Programming Language :: Python :: 3 :: Only
Classifier: Programming Language :: Python :: 3.10
Classifier: Programming Language :: Python :: 3.7
Classifier: Programming Language :: Python :: 3.8
Classifier: Programming Language :: Python :: 3.9
Classifier: Topic :: Software Development :: Libraries
Project-URL: Documentation, https://ozcanyarimdunya.github.io/py3html/
Project-URL: Repository, https://github.com/ozcanyarimdunya/py3html
